{"chunk_definitions":[{"row":7,"row_count":1,"visible":true,"expansion_state":0,"options":{"engine":"r","label":"setup","include":false},"document_id":"0583AFD8","chunk_id":"csetup_chunk","chunk_label":"setup"},{"row":212,"row_count":1,"visible":true,"expansion_state":0,"options":{"engine":"r","label":"unnamed-chunk-82"},"document_id":"5CD25965","chunk_id":"cohmudm0b4d1h","chunk_label":"unnamed-chunk-7"},{"row":243,"row_count":1,"visible":true,"expansion_state":0,"options":{"engine":"r","label":"unnamed-chunk-86"},"document_id":"5CD25965","chunk_id":"c17xwrhvkxpl2","chunk_label":"unnamed-chunk-8"},{"row":290,"row_count":1,"visible":true,"expansion_state":0,"options":{"engine":"r","label":"unnamed-chunk-87"},"document_id":"5CD25965","chunk_id":"cyf5iba41d3mp","chunk_label":"unnamed-chunk-10"},{"row":341,"row_count":1,"visible":true,"expansion_state":0,"options":{"engine":"r","label":"unnamed-chunk-3"},"document_id":"0583AFD8","chunk_id":"c6gjucibwscxy","chunk_label":"unnamed-chunk-13"},{"row":350,"row_count":1,"visible":true,"expansion_state":0,"options":{"engine":"r","label":"unnamed-chunk-4"},"document_id":"5CD25965","chunk_id":"cdqvvv27xr87z","chunk_label":"unnamed-chunk-14"},{"row":364,"row_count":1,"visible":true,"expansion_state":0,"options":{"engine":"r","label":"unnamed-chunk-17"},"document_id":"5CD25965","chunk_id":"crhm64ro7qvg2","chunk_label":"unnamed-chunk-15"},{"row":417,"row_count":1,"visible":true,"expansion_state":0,"options":{"engine":"r","label":"unnamed-chunk-77"},"document_id":"389F1DB6","chunk_id":"cwbyxz88of7oa","chunk_label":"unnamed-chunk-18"},{"row":602,"row_count":1,"visible":true,"expansion_state":0,"options":{"engine":"r","label":"unnamed-chunk-4"},"document_id":"EF2CEF25","chunk_id":"cbo5ouzqgbgxv","chunk_label":"unnamed-chunk-25"},{"row":644,"row_count":1,"visible":true,"expansion_state":0,"options":{"engine":"r","label":"unnamed-chunk-5"},"document_id":"EF2CEF25","chunk_id":"cwphnfe716kpb","chunk_label":"unnamed-chunk-26"},{"row":704,"row_count":1,"visible":true,"expansion_state":0,"options":{"engine":"r","label":"unnamed-chunk-6"},"document_id":"EF2CEF25","chunk_id":"ce7ka2946tyr7","chunk_label":"unnamed-chunk-27"},{"row":754,"row_count":1,"visible":true,"expansion_state":0,"options":{"engine":"r","label":"unnamed-chunk-7"},"document_id":"EF2CEF25","chunk_id":"c4yozmfkmgove","chunk_label":"unnamed-chunk-28"},{"row":763,"row_count":1,"visible":true,"expansion_state":0,"options":{"engine":"r","label":"unnamed-chunk-51"},"document_id":"389F1DB6","chunk_id":"cjz136lmwek49","chunk_label":"unnamed-chunk-29"},{"row":778,"row_count":1,"visible":true,"expansion_state":0,"options":{"engine":"r","label":"unnamed-chunk-53"},"document_id":"0583AFD8","chunk_id":"cr8rxcdzamdpl","chunk_label":"unnamed-chunk-30"},{"row":788,"row_count":1,"visible":true,"expansion_state":0,"options":{"engine":"r","label":"unnamed-chunk-50"},"document_id":"0583AFD8","chunk_id":"c0q9gbju3iz0k","chunk_label":"unnamed-chunk-31"},{"row":798,"row_count":1,"visible":true,"expansion_state":0,"options":{"engine":"r","label":"unnamed-chunk-12"},"document_id":"0583AFD8","chunk_id":"c1cdj3u1h58ga","chunk_label":"unnamed-chunk-32"},{"row":1091,"row_count":1,"visible":true,"expansion_state":0,"options":{"engine":"r","label":"unnamed-chunk-109"},"document_id":"389F1DB6","chunk_id":"c60g29lmo7flu","chunk_label":"unnamed-chunk-43"},{"row":1178,"row_count":1,"visible":true,"expansion_state":0,"options":{"engine":"r","label":"unnamed-chunk-49"},"document_id":"0583AFD8","chunk_id":"ceqmmmo8tyzpx","chunk_label":"unnamed-chunk-46"}],"doc_write_time":1638438579,"chunk_rendered_width":524,"working_dir":null,"default_chunk_options":{"echo":true}}